{
  "sfem": {
    "module": "buckling_app",
    "format": "buckling",
    "type": "model",
    "format_version": 1,
    "created": "2026-03-24T14:07:16",
    "name": "I-beam case 6",
    "description": ""
  },
  "data": {
    "member": {
      "name": "I-beam case 6",
      "N_Ed_kN": -8000.0,
      "A_mm2": 94800.0,
      "Iy_mm4": 5287222784.81,
      "Iz_mm4": 1033240000.0,
      "fy_MPa": 275.0,
      "E_MPa": 200000.0,
      "L_m": 8.0,
      "mu_y": 0.7,
      "mu_z": 0.7,
      "curve_y": "d",
      "curve_z": "d",
      "gamma_M0": 1.0,
      "gamma_M1": 1.0
    }
  }
}